liboqs/__init__.py
liboqs/liboqs.py
liboqs/liboqs32bit.so
liboqs/liboqs64bit.dll
liboqs/liboqs64bit.so
liboqs/rand.py
liboqs-0.9.0.dist-info/LICENSE
liboqs-0.9.0.dist-info/METADATA
liboqs-0.9.0.dist-info/WHEEL
liboqs-0.9.0.dist-info/top_level.txt
liboqs-0.9.0.dist-info/RECORD
