Metadata-Version: 2.1
Name: liboqs
Version: 0.9.0
Summary: Unofficial liboqs-python library with precompiled liboqs libraries
Home-page: https://github.com/FunDan3/liboqs-python-pip/
Author: Fun_Dan3
Author-email: dfr34560@gmail.com
Project-URL: Bug Tracker, https://github.com/FunDan3/liboqs-python-pip/issues
Classifier: Programming Language :: Python :: 3
Classifier: License :: OSI Approved :: GNU General Public License v3 (GPLv3)
Classifier: Operating System :: OS Independent
Requires-Python: >=3.8
License-File: LICENSE
